wraphper/__init__.py
wraphper-0.0.2.dist-info/LICENSE
wraphper-0.0.2.dist-info/METADATA
wraphper-0.0.2.dist-info/WHEEL
wraphper-0.0.2.dist-info/top_level.txt
wraphper-0.0.2.dist-info/RECORD
