Metadata-Version: 2.1
Name: wraphper
Version: 0.0.2
Summary: Python wrappers for PHP functions, when you just can't shake it.
Home-page: https://github.com/aalaap/wraphper
Author: Aalaap Ghag
License: UNKNOWN
Platform: UNKNOWN
Classifier: Programming Language :: Python :: 3
Classifier: Programming Language :: Python :: 2
Classifier: Programming Language :: PHP
Classifier: License :: OSI Approved :: MIT License
Classifier: Operating System :: OS Independent
